Metadata-Version: 2.1
Name: un-search-results-scraper
Version: 1.0.0
Summary: A python library to search keyword and scrape search results data from un.org .
Home-page: https://datakund.com
Author: DataKund
Author-email: datakund@gmail.com
License: Apache License 2.0
Keywords: un python bot_studio scraper web-scraping search-results search keyword
Platform: UNKNOWN
